pymasep/__init__.py
pymasep/app.py
pymasep/circular_head_list.py
pymasep/dices.py
pymasep/logger.py
pymasep/utils.py
pymasep/application/__init__.py
pymasep/application/connected_sub_app_info.py
pymasep/application/sub_app.py
pymasep/application/sub_app_state.py
pymasep/common/__init__.py
pymasep/common/action.py
pymasep/common/agent.py
pymasep/common/base_object.py
pymasep/common/belief.py
pymasep/common/characteristic.py
pymasep/common/container.py
pymasep/common/controller.py
pymasep/common/environment.py
pymasep/common/game.py
pymasep/common/intention.py
pymasep/common/object.py
pymasep/common/object_state.py
pymasep/common/state.py
pymasep/common/exception/__init__.py
pymasep/common/exception/constraint_exception.py
pymasep/common/exception/creation_exception.py
pymasep/common/initializer/__init__.py
pymasep/common/initializer/initializer.py
pymasep/common/initializer/initializer_charac_interface.py
pymasep/common/initializer/initializer_charac_interface_shared.py
pymasep/common/initializer/initializer_container.py
pymasep/common/initializer/initializer_container_interface.py
pymasep/common/initializer/initializer_fixed.py
pymasep/common/initializer/initializer_object.py
pymasep/common/initializer/initializer_object_interface.py
pymasep/common/initializer/initializer_object_state.py
pymasep/common/initializer/initializer_object_state_interface.py
pymasep/common/math/__init__.py
pymasep/common/math/grid_tools.py
pymasep/common/template/__init__.py
pymasep/common/template/system_templates.py
pymasep/common/template/template.py
pymasep/communication/__init__.py
pymasep/communication/base_threaded_communication.py
pymasep/communication/client.py
pymasep/communication/frame.py
pymasep/communication/message.py
pymasep/communication/server.py
pymasep/communication/socket_handler.py
pymasep/communication/socket_handler_queue.py
pymasep/engine/__init__.py
pymasep/engine/engine.py
pymasep/engine/environment_engine.py
pymasep/engine/external_controller.py
pymasep-0.2.dist-info/LICENSE
pymasep-0.2.dist-info/METADATA
pymasep-0.2.dist-info/WHEEL
pymasep-0.2.dist-info/top_level.txt
pymasep-0.2.dist-info/RECORD
