Metadata-Version: 2.1
Name: pymasep
Version: 0.2
Summary: Multiagent system engine plateform library in python
Author-email: Julien Laumonier <laumonierjulien@gmail.com>
Project-URL: Homepage, https://gitlab.com/jlaumonier/pymasep
Project-URL: Bug Tracker, https://gitlab.com/jlaumonier/pymasep/-/issues
Project-URL: Documentation, https://pymasep.readthedocs.io/en/latest/
Classifier: Programming Language :: Python :: 3
Classifier: License :: OSI Approved :: MIT License
Classifier: Operating System :: OS Independent
Requires-Python: >=3.10
License-File: LICENSE
Requires-Dist: pygame-ce ~=2.5.0
Requires-Dist: pygame-gui ==0.6.12
Requires-Dist: networkx[default] ~=3.3
Requires-Dist: networkx-query ~=2.1.0
Requires-Dist: omegaconf ~=2.3.0
Requires-Dist: hydra-core ~=1.3.2
Requires-Dist: Unidecode ~=1.3.8
Requires-Dist: opencv-python ~=4.10.0.84
Requires-Dist: pytest ==7.3.2
Requires-Dist: setuptools
